miyabiname/__init__.py
miyabiname/helloworld.py
miyabiname-1.0.2.dist-info/METADATA
miyabiname-1.0.2.dist-info/WHEEL
miyabiname-1.0.2.dist-info/entry_points.txt
miyabiname-1.0.2.dist-info/top_level.txt
miyabiname-1.0.2.dist-info/RECORD
