Metadata-Version: 2.1
Name: miyabiname
Version: 1.0.2
Summary: helloCommand
Home-page: https://github.com/MiyabiShibayama/miybiname
Author: MiyabiShibayama
Author-email: miyabi@osstech.co.jp
License: MIT
Platform: UNKNOWN
Requires-Dist: Click (==7.0)
